Metadata-Version: 1.1
Name: anyvc
Version: 0.3.7.1
Summary: Library to access any version control system.
Home-page: http://www.bitbucket.org/RonnyPfannschmidt/anyvc/
Author: Ronny Pfannschmidt
Author-email: Ronny.Pfannschmidt@gmx.de
License: GNU GPL2 (or later) as published by the FSF
Platform: UNKNOWN
Classifier: Intended Audience :: Developers
